gramadan/__init__.py
gramadan/adjective.py
gramadan/features.py
gramadan/noun.py
gramadan/np.py
gramadan/opers.py
gramadan/plural_info.py
gramadan/possessive.py
gramadan/pp.py
gramadan/preposition.py
gramadan/printer_neid.py
gramadan/py.typed
gramadan/singular_info.py
gramadan/tester/__init__.py
gramadan/tester/consistency.py
gramadan/tester/program.py
gramadan/tester/quality_control.py
gramadan/tester/testpossessives.py
gramadan/utils.py
gramadan/v2/__init__.py
gramadan/v2/database.py
gramadan/v2/noun.py
gramadan/v2/noun_cli.py
gramadan/v2/noun_empirical.py
gramadan/v2/noun_nualeargais.py
gramadan/v2/other_groups.py
gramadan/v2/semantic_groups.py
gramadan/verb.py
gramadan/vp.py
gramadan_py-0.1.1.dist-info/WHEEL
gramadan_py-0.1.1.dist-info/METADATA
gramadan_py-0.1.1.dist-info/RECORD
