Metadata-Version: 2.1
Name: gramadan-py
Version: 0.1.1
Summary: Pure Python implementation of michmech's C# Gramadán utility for manipulating the Irish National Morphology Database
License: MIT
Author: Phil Weir (Python conversion Michal Měchura's work)
Author-email: phil.t.weir@gmail.com
Requires-Python: >=3.9,<4.0
Classifier: License :: OSI Approved :: MIT License
Classifier: Programming Language :: Python :: 3
Classifier: Programming Language :: Python :: 3.10
Classifier: Programming Language :: Python :: 3.9
Requires-Dist: lxml (>=4.7.1,<5.0.0)
Requires-Dist: tabulate (>=0.8.9,<0.9.0)
